<Brushes>

  <Brush Name="Culture.Banner.Layer.4">
    <Layers>
      <BrushLayer Name="Default"  />
    </Layers>
    <Styles>
      <Style Name="battania">
        <BrushLayer Name="Default" Sprite="CharacterCreation\Culture\battania_4" />
      </Style>
      <Style Name="empire">
        <BrushLayer Name="Default" Sprite="CharacterCreation\Culture\empire_4" />
      </Style>
      <Style Name="sturgia">
        <BrushLayer Name="Default" Sprite="CharacterCreation\Culture\sturgia_4" />
      </Style>
      <Style Name="aserai">
        <BrushLayer Name="Default" Sprite="CharacterCreation\Culture\aserai_4" />
      </Style>
      <Style Name="khuzait">
        <BrushLayer Name="Default" Sprite="CharacterCreation\Culture\khuzait_4" />
      </Style>
      <Style Name="vlandia">
        <BrushLayer Name="Default" Sprite="CharacterCreation\Culture\vlandia_4" />
      </Style>
      <Style Name="mousillon">
        <BrushLayer Name="Default" Sprite="CharacterCreation\Culture\mousillon_4" />
      </Style>
    </Styles>
  </Brush>

  <Brush Name="Culture.Banner.Layer.3">
    <Layers>
      <BrushLayer Name="Default"  />
    </Layers>
    <Styles>
      <Style Name="battania">
        <BrushLayer Name="Default" Sprite="CharacterCreation\Culture\battania_3" />
      </Style>
      <Style Name="empire">
        <BrushLayer Name="Default" Sprite="CharacterCreation\Culture\empire_3" />
      </Style>
      <Style Name="sturgia">
        <BrushLayer Name="Default" Sprite="CharacterCreation\Culture\sturgia_3" />
      </Style>
      <Style Name="aserai">
        <BrushLayer Name="Default" Sprite="CharacterCreation\Culture\aserai_3" />
      </Style>
      <Style Name="khuzait">
        <BrushLayer Name="Default" Sprite="CharacterCreation\Culture\khuzait_3" />
      </Style>
      <Style Name="vlandia">
        <BrushLayer Name="Default" Sprite="CharacterCreation\Culture\vlandia_3" />
      </Style>
      <Style Name="mousillon">
        <BrushLayer Name="Default" Sprite="CharacterCreation\Culture\mousillon_3" />
      </Style>
    </Styles>
  </Brush>

  <Brush Name="Culture.Banner.Layer.2">
    <Layers>
      <BrushLayer Name="Default"  />
    </Layers>
    <Styles>
      <Style Name="battania">
        <BrushLayer Name="Default" Sprite="CharacterCreation\Culture\battania_2" />
      </Style>
      <Style Name="empire">
        <BrushLayer Name="Default" Sprite="CharacterCreation\Culture\empire_2" />
      </Style>
      <Style Name="sturgia">
        <BrushLayer Name="Default" Sprite="CharacterCreation\Culture\sturgia_2" />
      </Style>
      <Style Name="aserai">
        <BrushLayer Name="Default" Sprite="CharacterCreation\Culture\aserai_2" />
      </Style>
      <Style Name="khuzait">
        <BrushLayer Name="Default" Sprite="CharacterCreation\Culture\khuzait_2" />
      </Style>
      <Style Name="vlandia">
        <BrushLayer Name="Default" Sprite="CharacterCreation\Culture\vlandia_2" />
      </Style>
      <Style Name="mousillon">
        <BrushLayer Name="Default" Sprite="CharacterCreation\Culture\mousillon_2" />
      </Style>
    </Styles>
  </Brush>

  <Brush Name="Culture.Banner.Layer.1">
    <Layers>
      <BrushLayer Name="Default"  />
    </Layers>
    <Styles>
      <Style Name="battania">
        <BrushLayer Name="Default" Sprite="CharacterCreation\Culture\battania_1" />
      </Style>
      <Style Name="empire">
        <BrushLayer Name="Default" Sprite="CharacterCreation\Culture\empire_1" />
      </Style>
      <Style Name="sturgia">
        <BrushLayer Name="Default" Sprite="CharacterCreation\Culture\sturgia_1" />
      </Style>
      <Style Name="aserai">
        <BrushLayer Name="Default" Sprite="CharacterCreation\Culture\aserai_1" />
      </Style>
      <Style Name="khuzait">
        <BrushLayer Name="Default" Sprite="CharacterCreation\Culture\khuzait_1" />
      </Style>
      <Style Name="vlandia">
        <BrushLayer Name="Default" Sprite="CharacterCreation\Culture\vlandia_1" />
      </Style>
      <Style Name="mousillon">
        <BrushLayer Name="Default" Sprite="CharacterCreation\Culture\mousillon_1" />
      </Style>
    </Styles>
  </Brush>

</Brushes>